<?xml version = '1.0' encoding = 'UTF-8'?>
<TableProxyOraclev12c class="oracle.dbtools.crest.model.design.storage.oracle.v12c.TableProxyOraclev12c" name="RESTAURANT" directorySegmentName="seg_0" id="F98642B2-C40C-F2F3-1CA9-59A50672602B">
<createdBy>My Computer</createdBy>
<createdTime>2022-12-23 11:44:42 UTC</createdTime>
<ownerDesignName>Restaurant</ownerDesignName>
<logging>YES</logging>
<partitionedRowMovement>DISABLE</partitionedRowMovement>
<temporaryChanged>false</temporaryChanged>
<accessDriverType>oracle_loader</accessDriverType>
<rejectLimit></rejectLimit>
<columnProxies itemClass="oracle.dbtools.crest.model.design.storage.oracle.v12c.ColumnProxyOraclev12c">
<ColumnProxy name="Adresa_restaurant" id="18C2F386-96E7-0BD2-C3E3-988F0065BF2B">
<createdBy>My Computer</createdBy>
<createdTime>2022-12-23 11:44:42 UTC</createdTime>
<ownerDesignName>Restaurant</ownerDesignName>
</ColumnProxy>
<ColumnProxy name="Id_restaurant" id="3F58ED89-F901-3EEB-3E59-E625CF0F26B5">
<createdBy>My Computer</createdBy>
<createdTime>2022-12-23 11:44:42 UTC</createdTime>
<ownerDesignName>Restaurant</ownerDesignName>
<autoIncrementDDL>IDENTITY_CLAUSE</autoIncrementDDL>
<notnullConstraintnameChanged>true</notnullConstraintnameChanged>
</ColumnProxy>
<ColumnProxy name="Nume_restaurant" id="43787E18-3E78-610E-33E7-1114758736D5">
<createdBy>My Computer</createdBy>
<createdTime>2022-12-23 11:44:42 UTC</createdTime>
<ownerDesignName>Restaurant</ownerDesignName>
</ColumnProxy>
<ColumnProxy name="Telefon_restaurant" id="D17B8BCE-F496-3154-91CF-BF981950678A">
<createdBy>My Computer</createdBy>
<createdTime>2022-12-23 11:44:42 UTC</createdTime>
<ownerDesignName>Restaurant</ownerDesignName>
</ColumnProxy>
<ColumnProxy name="Nr_sali" id="F3D1D8A0-14BF-FC4E-F2E2-38EE98A7F3A1">
<createdBy>My Computer</createdBy>
<createdTime>2022-12-23 11:44:42 UTC</createdTime>
<ownerDesignName>Restaurant</ownerDesignName>
</ColumnProxy>
</columnProxies>
<primaryKeys>
<PrimaryKey class="oracle.dbtools.crest.model.design.storage.oracle.v10g.PKProxyOraclev10g" name="RESTAURANT_PK" id="499FDE01-D5F5-D976-2A21-11224A15BCF0">
<createdBy>My Computer</createdBy>
<createdTime>2022-12-23 11:44:42 UTC</createdTime>
<ownerDesignName>Restaurant</ownerDesignName>
<indexSort>SORTED</indexSort>
</PrimaryKey>
</primaryKeys>
<uniqueKeys>
<UniqueKey class="oracle.dbtools.crest.model.design.storage.oracle.v10g.UniqueOraclev10g" name="Restaurant_adresa_telefon_UK" id="A0865D86-F7A4-E1BA-D075-0B6831A80FF6">
<createdBy>My Computer</createdBy>
<createdTime>2022-12-23 11:44:42 UTC</createdTime>
<ownerDesignName>Restaurant</ownerDesignName>
<indexSort>SORTED</indexSort>
</UniqueKey>
</uniqueKeys>
</TableProxyOraclev12c>